navground.dylibs/libgeos.3.13.0.dylib
navground.dylibs/libhdf5.310.5.0.dylib
navground.dylibs/libnavground_core.dylib
navground.dylibs/libnavground_sim.dylib
navground/core/__init__.py
navground/core/__main__.py
navground/core/_navground.cpython-313-darwin.so
navground/core/_navground.pyi
navground/core/behavior_modulations/__init__.py
navground/core/behaviors/__init__.py
navground/core/behaviors/dummy.py
navground/core/behaviors/social_force.py
navground/core/command.py
navground/core/echo.py
navground/core/info.py
navground/core/kinematics/__init__.py
navground/core/list_plugins.py
navground/core/main.py
navground/core/print_schema.py
navground/core/property.py
navground/core/py.typed
navground/core/schema.py
navground/core/utils.py
navground/core/validate.py
navground/sim/__init__.py
navground/sim/__main__.py
navground/sim/_navground_sim.cpython-313-darwin.so
navground/sim/_navground_sim.pyi
navground/sim/bounds.py
navground/sim/echo.py
navground/sim/info.py
navground/sim/list_plugins.py
navground/sim/main.py
navground/sim/notebook.py
navground/sim/print_schema.py
navground/sim/py.typed
navground/sim/pyplot_helpers.py
navground/sim/real_time.py
navground/sim/record_video.py
navground/sim/recorded_experiment.py
navground/sim/replay.py
navground/sim/run.py
navground/sim/run_mp.py
navground/sim/run_rt.py
navground/sim/sample.py
navground/sim/scenarios/__init__.py
navground/sim/schema.py
navground/sim/state_estimations/__init__.py
navground/sim/state_estimations/lidar.py
navground/sim/tasks/__init__.py
navground/sim/tasks/path.py
navground/sim/ui/__init__.py
navground/sim/ui/common.py
navground/sim/ui/render.py
navground/sim/ui/templates/client.js
navground/sim/ui/templates/quadrotor.svg
navground/sim/ui/templates/robomaster_ep.svg
navground/sim/ui/templates/style.css
navground/sim/ui/templates/svg.pan-zoom.min.js
navground/sim/ui/templates/thymio.svg
navground/sim/ui/templates/view.html
navground/sim/ui/templates/world.html
navground/sim/ui/templates/world.svg
navground-0.6.0.dist-info/METADATA
navground-0.6.0.dist-info/WHEEL
navground-0.6.0.dist-info/entry_points.txt
navground-0.6.0.dist-info/top_level.txt
navground-0.6.0.dist-info/RECORD
