Metadata-Version: 2.4
Name: navground
Version: 0.6.0
Summary: A playground to experiment with navigation algorithms.
Author-email: Jerome Guzzi <jerome@idsia.ch>
Maintainer-email: Jerome Guzzi <jerome@idsia.ch>
Project-URL: Homepage, https://github.com/idsia-robotics/navground
Project-URL: Documentation, https://idsia-robotics.github.io/navground
Project-URL: Repository, https://github.com/idsia-robotics/navground.git
Project-URL: Bug Tracker, https://github.com/idsia-robotics/navground/issues
Project-URL: Changelog, https://github.com/idsia-robotics/navground/blob/main/CHANGELOG.md
Classifier: Development Status :: 4 - Beta
Classifier: Programming Language :: Python
Requires-Python: >=3.10
Requires-Dist: numpy>=1.21
Requires-Dist: PyYaml
Provides-Extra: all
Requires-Dist: tqdm; extra == "all"
Requires-Dist: h5py; extra == "all"
Requires-Dist: websockets; extra == "all"
Requires-Dist: cairosvg; extra == "all"
Requires-Dist: moviepy; extra == "all"
Requires-Dist: Jinja2; extra == "all"
Requires-Dist: jsonschema>=4.18; extra == "all"
Requires-Dist: shapely; extra == "all"
